{"grades":[{"county":"Lake of the Woods","grade":"A","color":"#3c8259"},
    {"county":"Red Lake","grade":"A","color":"#3c8259"},
    {"county":"Big Stone","grade":"B","color":"#d8e4d0"},
    {"county":"Carlton","grade":"B","color":"#d8e4d0"},
    {"county":"Cass","grade":"B","color":"#d8e4d0"},
    {"county":"Hennepin","grade":"B","color":"#d8e4d0"},
    {"county":"Kittson","grade":"B","color":"#d8e4d0"},
    {"county":"Lake","grade":"B","color":"#d8e4d0"},
    {"county":"Mahnomen","grade":"B","color":"#d8e4d0"},
    {"county":"Marshall","grade":"B","color":"#d8e4d0"},
    {"county":"Traverse","grade":"B","color":"#d8e4d0"},
    {"county":"Fillmore","grade":"B-","color":"#d8e4d0"},
    {"county":"Goodhue","grade":"B-","color":"#d8e4d0"},
    {"county":"Itasca","grade":"B-","color":"#d8e4d0"},
    {"county":"Polk","grade":"B-","color":"#d8e4d0"},
    {"county":"Ramsey","grade":"B-","color":"#d8e4d0"},
    {"county":"St. Louis","grade":"B-","color":"#d8e4d0"},
    {"county":"Aitkin","grade":"C","color":"#F7F7F7"},
    {"county":"Beltrami","grade":"C","color":"#F7F7F7"},
    {"county":"Chippewa","grade":"C","color":"#F7F7F7"},
    {"county":"Clay","grade":"C","color":"#F7F7F7"},
    {"county":"Cottonwood","grade":"C","color":"#F7F7F7"},
    {"county":"Grant","grade":"C","color":"#F7F7F7"},
    {"county":"Hubbard","grade":"C","color":"#F7F7F7"},
    {"county":"Kanabec","grade":"C","color":"#F7F7F7"},
    {"county":"Koochiching","grade":"C","color":"#F7F7F7"},
    {"county":"Le Sueur","grade":"C","color":"#F7F7F7"},
    {"county":"Murray","grade":"C","color":"#F7F7F7"},
    {"county":"Nicollet","grade":"C","color":"#F7F7F7"},
    {"county":"Norman","grade":"C","color":"#F7F7F7"},
    {"county":"Olmsted","grade":"C","color":"#F7F7F7"},
    {"county":"Pennington","grade":"C","color":"#F7F7F7"},
    {"county":"Pope","grade":"C","color":"#F7F7F7"},
    {"county":"Scott","grade":"C","color":"#F7F7F7"},
    {"county":"Stearns","grade":"C","color":"#F7F7F7"},
    {"county":"Stevens","grade":"C","color":"#F7F7F7"},
    {"county":"Swift","grade":"C","color":"#F7F7F7"},
    {"county":"Blue Earth","grade":"C-","color":"#F7F7F7"},
    {"county":"Carver","grade":"C-","color":"#F7F7F7"},
    {"county":"Dakota","grade":"C-","color":"#F7F7F7"},
    {"county":"Douglas","grade":"C-","color":"#F7F7F7"},
    {"county":"Houston","grade":"C-","color":"#F7F7F7"},
    {"county":"Roseau","grade":"C-","color":"#F7F7F7"},
    {"county":"Washington","grade":"C-","color":"#F7F7F7"},
    {"county":"Winona","grade":"C-","color":"#F7F7F7"},
    {"county":"Anoka","grade":"D","color":"#D9D3EB"},
    {"county":"Becker","grade":"D","color":"#D9D3EB"},
    {"county":"Chisago","grade":"D","color":"#D9D3EB"},
    {"county":"Cook","grade":"D","color":"#D9D3EB"},
    {"county":"Crow Wing","grade":"D","color":"#D9D3EB"},
    {"county":"Faribault","grade":"D","color":"#D9D3EB"},
    {"county":"Jackson","grade":"D","color":"#D9D3EB"},
    {"county":"Kandiyohi","grade":"D","color":"#D9D3EB"},
    {"county":"Lac Qui Parle","grade":"D","color":"#D9D3EB"},
    {"county":"Lincoln","grade":"D","color":"#D9D3EB"},
    {"county":"Martin","grade":"D","color":"#D9D3EB"},
    {"county":"Meeker","grade":"D","color":"#D9D3EB"},
    {"county":"Pine","grade":"D","color":"#D9D3EB"},
    {"county":"Pipestone","grade":"D","color":"#D9D3EB"},
    {"county":"Redwood","grade":"D","color":"#D9D3EB"},
    {"county":"Renville","grade":"D","color":"#D9D3EB"},
    {"county":"Rock","grade":"D","color":"#D9D3EB"},
    {"county":"Sherburne","grade":"D","color":"#D9D3EB"},
    {"county":"Sibley","grade":"D","color":"#D9D3EB"},
    {"county":"Steele","grade":"D","color":"#D9D3EB"},
    {"county":"Todd","grade":"D","color":"#D9D3EB"},
    {"county":"Wabasha","grade":"D","color":"#D9D3EB"},
    {"county":"Wadena","grade":"D","color":"#D9D3EB"},
    {"county":"Waseca","grade":"D","color":"#D9D3EB"},
    {"county":"Wilkin","grade":"D","color":"#D9D3EB"},
    {"county":"Wright","grade":"D","color":"#D9D3EB"},
    {"county":"Yellow Medicine","grade":"D","color":"#D9D3EB"},
    {"county":"Benton","grade":"D-","color":"#D9D3EB"},
    {"county":"Brown","grade":"D-","color":"#D9D3EB"},
    {"county":"Dodge","grade":"D-","color":"#D9D3EB"},
    {"county":"Isanti","grade":"D-","color":"#D9D3EB"},
    {"county":"Lyon","grade":"D-","color":"#D9D3EB"},
    {"county":"McLeod","grade":"D-","color":"#D9D3EB"},
    {"county":"Mille Lacs","grade":"D-","color":"#D9D3EB"},
    {"county":"Morrison","grade":"D-","color":"#D9D3EB"},
    {"county":"Mower","grade":"D-","color":"#D9D3EB"},
    {"county":"Otter Tail","grade":"D-","color":"#D9D3EB"},
    {"county":"Rice","grade":"D-","color":"#D9D3EB"},
    {"county":"Watonwan","grade":"D-","color":"#D9D3EB"},
    {"county":"Clearwater","grade":"F","color":"#4A4061"},
    {"county":"Freeborn","grade":"F","color":"#4A4061"},
    {"county":"Nobles","grade":"F","color":"#4A4061"}]}